[
{"college": "CAS", "department": "AA", "number": "296", "code": "A1", "availability": false},
{"college": "CAS", "department": "AA", "number": "114", "code": "A1", "availability": false},
{"college": "CAS", "department": "AA", "number": "114", "code": "B1", "availability": false},
{"college": "CAS", "department": "AA", "number": "114", "code": "C1", "availability": false},
{"college": "CAS", "department": "AA", "number": "114", "code": "D1", "availability": false},
{"college": "CAS", "department": "AA", "number": "114", "code": "E1", "availability": false},
{"college": "CAS", "department": "AA", "number": "234", "code": "A1", "availability": false},
{"college": "CAS", "department": "AA", "number": "313", "code": "A1", "availability": false},
{"college": "CAS", "department": "AA", "number": "305", "code": "A1", "availability": false},
{"college": "CAS", "department": "AA", "number": "371", "code": "A1", "availability": false},
{"college": "CAS", "department": "AA", "number": "207", "code": "A1", "availability": false},
{"college": "CAS", "department": "AA", "number": "207", "code": "A2", "availability": false},
{"college": "CAS", "department": "AA", "number": "207", "code": "A3", "availability": false},
{"college": "CAS", "department": "AA", "number": "207", "code": "A4", "availability": false},
{"college": "CAS", "department": "AA", "number": "132", "code": "A1", "availability": false},
{"college": "CAS", "department": "AA", "number": "308", "code": "A1", "availability": false},
{"college": "CAS", "department": "AA", "number": "103", "code": "A1", "availability": true}
]